{
	"backtraceGraph" : 
	{
		"commands" : 
		[
			"install",
			"nuttx_add_library_internal",
			"nuttx_add_library"
		],
		"files" : 
		[
			"cmake/nuttx_add_library.cmake",
			"/Users/frostydev/workspace/MQP/Vanguard-RTOS/apps/builtin/CMakeLists.txt"
		],
		"nodes" : 
		[
			{
				"file" : 1
			},
			{
				"command" : 2,
				"file" : 1,
				"line" : 57,
				"parent" : 0
			},
			{
				"command" : 1,
				"file" : 0,
				"line" : 202,
				"parent" : 1
			},
			{
				"command" : 0,
				"file" : 0,
				"line" : 57,
				"parent" : 2
			}
		]
	},
	"installers" : 
	[
		{
			"backtrace" : 3,
			"component" : "Unspecified",
			"destination" : "lib",
			"paths" : 
			[
				"apps/builtin/libapps_builtin.a"
			],
			"targetId" : "apps_builtin::@54258d57ec9fedbeef7c",
			"targetIndex" : 5,
			"type" : "target"
		}
	],
	"paths" : 
	{
		"build" : "apps/builtin",
		"source" : "/Users/frostydev/workspace/MQP/Vanguard-RTOS/apps/builtin"
	}
}
